nomad_camels_driver_andor_newton/__init__.py
nomad_camels_driver_andor_newton/andor_newton.py
nomad_camels_driver_andor_newton/andor_newton_config.py
nomad_camels_driver_andor_newton/andor_newton_ophyd.py
nomad_camels_driver_andor_newton-0.1.5.dist-info/licenses/LICENSE.txt
nomad_camels_driver_andor_newton-0.1.5.dist-info/METADATA
nomad_camels_driver_andor_newton-0.1.5.dist-info/WHEEL
nomad_camels_driver_andor_newton-0.1.5.dist-info/top_level.txt
nomad_camels_driver_andor_newton-0.1.5.dist-info/RECORD
