Metadata-Version: 2.4
Name: nomad_camels_driver_andor_newton
Version: 0.1.5
Summary: This package provides everything to run an Andor Newton CCD.
Author-email: FAIRmat - HU Berlin <nomad-camels@fau.de>
Project-URL: GitHub Page, https://github.com/FAU-LAP/NOMAD-CAMELS
Project-URL: Documentation, https://fau-lap.github.io/NOMAD-CAMELS/doc/instruments/instruments.html
Classifier: Programming Language :: Python :: 3
Classifier: License :: OSI Approved :: GNU Lesser General Public License v2 (LGPLv2)
Requires-Python: >=3.9.6
License-File: LICENSE.txt
Requires-Dist: nomad-camels>=1.0.0
Requires-Dist: pylablib>=1.4.2
Dynamic: license-file
